[{"Pressed": "'s'"}, {"Held": "'s'"}, {"Released": "'s'"}, {"Pressed": "'h'"}, {"Held": "'h'"}, {"Released": "'h'"}, {"Pressed": "'y'"}, {"Held": "'y'"}, {"Released": "'y'"}, {"Pressed": "'a'"}, {"Held": "'a'"}, {"Released": "'a'"}, {"Pressed": "'m'"}, {"Held": "'m'"}, {"Released": "'m'"}, {"Pressed": "Key.enter"}, {"Held": "Key.enter"}, {"Released": "Key.enter"}, {"Pressed": "Key.ctrl_l"}, {"Held": "Key.ctrl_l"}, {"Held": "Key.ctrl_l"}, {"Held": "Key.ctrl_l"}, {"Held": "Key.ctrl_l"}, {"Held": "Key.ctrl_l"}, {"Held": "Key.ctrl_l"}, {"Held": "Key.ctrl_l"}, {"Held": "Key.ctrl_l"}, {"Held": "Key.ctrl_l"}, {"Held": "Key.ctrl_l"}, {"Held": "Key.ctrl_l"}, {"Held": "Key.ctrl_l"}, {"Held": "Key.ctrl_l"}, {"Held": "Key.ctrl_l"}, {"Held": "Key.ctrl_l"}, {"Held": "Key.ctrl_l"}, {"Held": "Key.ctrl_l"}, {"Held": "Key.ctrl_l"}, {"Held": "Key.ctrl_l"}, {"Held": "Key.ctrl_l"}, {"Held": "Key.ctrl_l"}, {"Held": "Key.ctrl_l"}, {"Held": "Key.ctrl_l"}, {"Held": "Key.ctrl_l"}, {"Held": "Key.ctrl_l"}, {"Held": "Key.ctrl_l"}, {"Held": "Key.ctrl_l"}, {"Held": "Key.ctrl_l"}, {"Held": "Key.ctrl_l"}, {"Held": "Key.ctrl_l"}, {"Held": "Key.ctrl_l"}, {"Held": "Key.ctrl_l"}, {"Held": "Key.ctrl_l"}, {"Held": "Key.ctrl_l"}, {"Held": "Key.ctrl_l"}, {"Held": "Key.ctrl_l"}, {"Held": "Key.ctrl_l"}, {"Held": "Key.ctrl_l"}, {"Held": "Key.ctrl_l"}, {"Held": "Key.ctrl_l"}, {"Held": "Key.ctrl_l"}, {"Held": "Key.ctrl_l"}, {"Held": "Key.ctrl_l"}, {"Held": "Key.ctrl_l"}, {"Held": "Key.ctrl_l"}, {"Held": "Key.ctrl_l"}, {"Held": "Key.ctrl_l"}, {"Held": "Key.ctrl_l"}, {"Held": "Key.ctrl_l"}, {"Held": "Key.ctrl_l"}, {"Held": "Key.ctrl_l"}, {"Held": "Key.ctrl_l"}, {"Held": "Key.ctrl_l"}, {"Held": "Key.ctrl_l"}, {"Released": "Key.ctrl_l"}, {"Pressed": "Key.ctrl_l"}, {"Held": "Key.ctrl_l"}, {"Held": "'\\x1a'"}, {"Released": "'\\x1a'"}, {"Released": "Key.ctrl_l"}, {"Pressed": "Key.ctrl_l"}, {"Held": "Key.ctrl_l"}, {"Released": "Key.ctrl_l"}, {"Pressed": "Key.ctrl_l"}, {"Held": "Key.ctrl_l"}, {"Held": "Key.ctrl_l"}, {"Held": "Key.ctrl_l"}, {"Held": "Key.ctrl_l"}, {"Held": "Key.ctrl_l"}, {"Held": "Key.ctrl_l"}, {"Released": "Key.ctrl_l"}, {"Pressed": "Key.ctrl_l"}, {"Held": "Key.ctrl_l"}, {"Held": "'\\x1a'"}, {"Released": "'\\x1a'"}, {"Pressed": "'\\x1a'"}, {"Held": "'\\x1a'"}, {"Released": "'\\x1a'"}, {"Pressed": "'\\x1a'"}, {"Held": "'\\x1a'"}, {"Released": "'\\x1a'"}, {"Pressed": "'\\x1a'"}, {"Held": "'\\x1a'"}, {"Released": "'\\x1a'"}, {"Released": "Key.ctrl_l"}, {"Pressed": "Key.ctrl_l"}, {"Held": "Key.ctrl_l"}, {"Held": "'\\x1a'"}, {"Released": "Key.ctrl_l"}, {"Released": "'z'"}, {"Pressed": "'s'"}, {"Held": "'s'"}, {"Released": "'s'"}, {"Pressed": "'h'"}, {"Held": "'h'"}, {"Released": "'h'"}, {"Pressed": "'y'"}, {"Held": "'y'"}, {"Released": "'y'"}, {"Pressed": "'a'"}, {"Held": "'a'"}, {"Released": "'a'"}, {"Pressed": "'m'"}, {"Held": "'m'"}, {"Released": "'m'"}]